pyrestyle.py
pyrestyle-0.0.8.dist-info/LICENSE
pyrestyle-0.0.8.dist-info/METADATA
pyrestyle-0.0.8.dist-info/WHEEL
pyrestyle-0.0.8.dist-info/entry_points.txt
pyrestyle-0.0.8.dist-info/top_level.txt
pyrestyle-0.0.8.dist-info/RECORD
