Metadata-Version: 2.1
Name: pyrestyle
Version: 0.0.8
Summary: Python style guide checker and This project based on pycodestyle
Home-page: https://github.com/CSID-DGU/2023-1-OPPS1-CGS-08/blob/main/pyrestyle.py
Author: Johann C. Rocholl, 2023-1-OPPS1-CGS-08
Author-email: kys00919@gmail.com
License: Expat license
Keywords: pyrestyle,pep8,PEP 8,PEP-8,PEP8
Classifier: Development Status :: 5 - Production/Stable
Classifier: Environment :: Console
Classifier: Intended Audience :: Developers
Classifier: License :: OSI Approved :: MIT License
Classifier: Operating System :: OS Independent
Classifier: Programming Language :: Python
Classifier: Programming Language :: Python :: 3
Classifier: Programming Language :: Python :: Implementation :: CPython
Classifier: Programming Language :: Python :: Implementation :: PyPy
Classifier: Topic :: Software Development :: Libraries :: Python Modules
Requires-Python: >=3.7
License-File: LICENSE
